assonant/__init__.py
assonant/_bluesky/__init__.py
assonant/_bluesky/data_parser.py
assonant/_bluesky/factories.py
assonant/_bluesky/exceptions/__init__.py
assonant/_bluesky/exceptions/bluesky_data_parser_exception.py
assonant/_bluesky/exceptions/bluesky_data_parser_factory_exception.py
assonant/_kafka/__init__.py
assonant/_kafka/producer.py
assonant/_nexus/__init__.py
assonant/_nexus/exceptions.py
assonant/_nexus/nexus_object_factory.py
assonant/data_classes/__init__.py
assonant/data_classes/assonant_data_class.py
assonant/data_classes/entry.py
assonant/data_classes/factories.py
assonant/data_classes/components/__init__.py
assonant/data_classes/components/aperture.py
assonant/data_classes/components/attenuator.py
assonant/data_classes/components/beam.py
assonant/data_classes/components/beam_stopper.py
assonant/data_classes/components/beamline.py
assonant/data_classes/components/bending_magnet.py
assonant/data_classes/components/bvs.py
assonant/data_classes/components/collimator.py
assonant/data_classes/components/component.py
assonant/data_classes/components/cryojet.py
assonant/data_classes/components/detector.py
assonant/data_classes/components/dewar.py
assonant/data_classes/components/fresnel_zone_plate.py
assonant/data_classes/components/granite_base.py
assonant/data_classes/components/grating.py
assonant/data_classes/components/mirror.py
assonant/data_classes/components/monochromator.py
assonant/data_classes/components/pinhole.py
assonant/data_classes/components/sample.py
assonant/data_classes/components/sensor.py
assonant/data_classes/components/shutter.py
assonant/data_classes/components/slit.py
assonant/data_classes/components/storage_ring.py
assonant/data_classes/components/undulator.py
assonant/data_classes/components/wiggler.py
assonant/data_classes/data_handlers/__init__.py
assonant/data_classes/data_handlers/axis.py
assonant/data_classes/data_handlers/data_field.py
assonant/data_classes/data_handlers/data_handler.py
assonant-2.7.1.dist-info/METADATA
assonant-2.7.1.dist-info/WHEEL
assonant-2.7.1.dist-info/top_level.txt
assonant-2.7.1.dist-info/RECORD
