Metadata-Version: 2.4
Name: assonant
Version: 2.7.1
Summary: (Meta)Data standardization package for Sirius, the 4th generation Brazilian synchrotron light source
Author: Data Science and Management Group @ GCD
Classifier: License :: OSI Approved :: GNU Lesser General Public License v3 or later (LGPLv3+)
Classifier: Programming Language :: Python :: 3.8
Classifier: Programming Language :: Python :: 3.9
Classifier: Programming Language :: Python :: 3.10
Classifier: Programming Language :: Python :: 3.11
Requires-Python: >=3.8
Provides-Extra: path-builder
Provides-Extra: naming-standards
Provides-Extra: data-logger
Requires-Dist: annotated-types>=0.7.0; extra == "data-logger"
Requires-Dist: h5py>=3.11.0; extra == "data-logger"
Requires-Dist: hdf5plugin>=5.0.0; extra == "data-logger"
Requires-Dist: nexusformat>=1.0.6; extra == "data-logger"
Requires-Dist: numpy; extra == "data-logger"
Requires-Dist: pydantic>=2.9.1; extra == "data-logger"
Requires-Dist: pydantic_core>=2.23.3; extra == "data-logger"
Requires-Dist: scipy>=1.10.1; extra == "data-logger"
Requires-Dist: typing_extensions>=4; extra == "data-logger"
Requires-Dist: pandas>=2.0.3; extra == "data-logger"
Requires-Dist: pyepics>=3.5.1; extra == "data-logger"
Requires-Dist: event-model>=1.22.3; extra == "data-logger"
Provides-Extra: full
Requires-Dist: annotated-types>=0.7.0; extra == "full"
Requires-Dist: h5py>=3.11.0; extra == "full"
Requires-Dist: hdf5plugin>=5.0.0; extra == "full"
Requires-Dist: nexusformat>=1.0.6; extra == "full"
Requires-Dist: numpy; extra == "full"
Requires-Dist: pydantic>=2.9.1; extra == "full"
Requires-Dist: pydantic_core>=2.23.3; extra == "full"
Requires-Dist: scipy>=1.10.1; extra == "full"
Requires-Dist: typing_extensions>=4; extra == "full"
Requires-Dist: pandas>=2.0.3; extra == "full"
Requires-Dist: pyepics>=3.5.1; extra == "full"
Requires-Dist: event-model==1.22.3; extra == "full"
Requires-Dist: confluent-kafka>=2.5.3; extra == "full"
Provides-Extra: dev
Requires-Dist: annotated-types>=0.7.0; extra == "dev"
Requires-Dist: h5py>=3.11.0; extra == "dev"
Requires-Dist: hdf5plugin>=5.0.0; extra == "dev"
Requires-Dist: nexusformat>=1.0.6; extra == "dev"
Requires-Dist: numpy; extra == "dev"
Requires-Dist: pydantic>=2.9.1; extra == "dev"
Requires-Dist: pydantic_core>=2.23.3; extra == "dev"
Requires-Dist: scipy>=1.10.1; extra == "dev"
Requires-Dist: typing_extensions>=4; extra == "dev"
Requires-Dist: pandas>=2.0.3; extra == "dev"
Requires-Dist: pyepics>=3.5.1; extra == "dev"
Requires-Dist: event-model==1.22.3; extra == "dev"
Requires-Dist: confluent-kafka>=2.5.3; extra == "dev"
Requires-Dist: black>=20.8b1; extra == "dev"
Requires-Dist: flake8>=6.0.0; extra == "dev"
Requires-Dist: flake8-docstrings>=1.6.0; extra == "dev"
Requires-Dist: isort>=5.12.0; extra == "dev"
Requires-Dist: interrogate>=1.5.0; extra == "dev"
Requires-Dist: pre-commit>=3.6.2; extra == "dev"
Requires-Dist: pytest==8.4.1; extra == "dev"
Requires-Dist: pytest-xdist==3.8.0; extra == "dev"
Requires-Dist: pytest-forked==1.6.0; extra == "dev"
